[
    {
        "name": "Elon Musk",
        "netWorth": 230000000000,
        "earningsPerSec": 510.53,
        "source": "Tesla, SpaceX",
        "type": "Billionaire"
    },
    {
        "name": "Bernard Arnault",
        "netWorth": 210000000000,
        "earningsPerSec": 466.13,
        "source": "LVMH",
        "type": "Billionaire"
    },
    {
        "name": "Jeff Bezos",
        "netWorth": 195000000000,
        "earningsPerSec": 432.84,
        "source": "Amazon",
        "type": "Billionaire"
    },
    {
        "name": "Mark Zuckerberg",
        "netWorth": 170000000000,
        "earningsPerSec": 377.35,
        "source": "Meta",
        "type": "Billionaire"
    },
    {
        "name": "Larry Ellison",
        "netWorth": 140000000000,
        "earningsPerSec": 310.76,
        "source": "Oracle",
        "type": "Billionaire"
    },
    {
        "name": "Warren Buffett",
        "netWorth": 135000000000,
        "earningsPerSec": 299.66,
        "source": "Berkshire",
        "type": "Billionaire"
    },
    {
        "name": "Bill Gates",
        "netWorth": 130000000000,
        "earningsPerSec": 288.56,
        "source": "Microsoft",
        "type": "Billionaire"
    },
    {
        "name": "Global Billionaire #178",
        "netWorth": 89720643653.47047,
        "earningsPerSec": 199.15,
        "source": "Real Estate",
        "type": "Billionaire"
    },
    {
        "name": "Global Billionaire #146",
        "netWorth": 89414272005.38933,
        "earningsPerSec": 198.47,
        "source": "Real Estate",
        "type": "Billionaire"
    },
    {
        "name": "Global Billionaire #132",
        "netWorth": 89366258484.95607,
        "earningsPerSec": 198.36,
        "source": "Real Estate",
        "type": "Billionaire"
    },
    {
        "name": "Global Billionaire #106",
        "netWorth": 89327644671.96432,
        "earningsPerSec": 198.28,
        "source": "Tech",
        "type": "Billionaire"
    },
    {
        "name": "Global Billionaire #43",
        "netWorth": 88305656295.28143,
        "earningsPerSec": 196.01,
        "source": "Energy",
        "type": "Billionaire"
    },
    {
        "name": "Global Billionaire #63",
        "netWorth": 87836773646.21808,
        "earningsPerSec": 194.97,
        "source": "Real Estate",
        "type": "Billionaire"
    },
    {
        "name": "Global Billionaire #162",
        "netWorth": 86760805795.34247,
        "earningsPerSec": 192.58,
        "source": "Finance",
        "type": "Billionaire"
    },
    {
        "name": "Global Billionaire #82",
        "netWorth": 86345983267.15456,
        "earningsPerSec": 191.66,
        "source": "Real Estate",
        "type": "Billionaire"
    },
    {
        "name": "Global Billionaire #181",
        "netWorth": 85964432778.13823,
        "earningsPerSec": 190.81,
        "source": "Real Estate",
        "type": "Billionaire"
    },
    {
        "name": "Global Billionaire #133",
        "netWorth": 84100963866.35567,
        "earningsPerSec": 186.68,
        "source": "Finance",
        "type": "Billionaire"
    },
    {
        "name": "Global Billionaire #95",
        "netWorth": 83693377333.46739,
        "earningsPerSec": 185.77,
        "source": "Finance",
        "type": "Billionaire"
    },
    {
        "name": "Global Billionaire #120",
        "netWorth": 83298832182.09575,
        "earningsPerSec": 184.9,
        "source": "Tech",
        "type": "Billionaire"
    },
    {
        "name": "Global Billionaire #32",
        "netWorth": 83088215340.58275,
        "earningsPerSec": 184.43,
        "source": "Tech",
        "type": "Billionaire"
    },
    {
        "name": "Global Billionaire #23",
        "netWorth": 82933871979.16302,
        "earningsPerSec": 184.09,
        "source": "Energy",
        "type": "Billionaire"
    },
    {
        "name": "Global Billionaire #166",
        "netWorth": 82493530329.97342,
        "earningsPerSec": 183.11,
        "source": "Finance",
        "type": "Billionaire"
    },
    {
        "name": "Global Billionaire #154",
        "netWorth": 82417860545.58594,
        "earningsPerSec": 182.94,
        "source": "Finance",
        "type": "Billionaire"
    },
    {
        "name": "Global Billionaire #184",
        "netWorth": 82327606372.71387,
        "earningsPerSec": 182.74,
        "source": "Finance",
        "type": "Billionaire"
    },
    {
        "name": "Global Billionaire #76",
        "netWorth": 81754354191.97952,
        "earningsPerSec": 181.47,
        "source": "Real Estate",
        "type": "Billionaire"
    },
    {
        "name": "Global Billionaire #92",
        "netWorth": 81693739334.10883,
        "earningsPerSec": 181.33,
        "source": "Tech",
        "type": "Billionaire"
    },
    {
        "name": "Global Billionaire #190",
        "netWorth": 81030995249.46973,
        "earningsPerSec": 179.86,
        "source": "Finance",
        "type": "Billionaire"
    },
    {
        "name": "Global Billionaire #179",
        "netWorth": 80520816489.49901,
        "earningsPerSec": 178.73,
        "source": "Retail",
        "type": "Billionaire"
    },
    {
        "name": "Global Billionaire #29",
        "netWorth": 80381084343.21504,
        "earningsPerSec": 178.42,
        "source": "Real Estate",
        "type": "Billionaire"
    },
    {
        "name": "Global Billionaire #61",
        "netWorth": 80310483242.83655,
        "earningsPerSec": 178.26,
        "source": "Tech",
        "type": "Billionaire"
    },
    {
        "name": "Global Billionaire #100",
        "netWorth": 80114439306.5424,
        "earningsPerSec": 177.83,
        "source": "Finance",
        "type": "Billionaire"
    },
    {
        "name": "Global Billionaire #192",
        "netWorth": 79089751400.54442,
        "earningsPerSec": 175.55,
        "source": "Tech",
        "type": "Billionaire"
    },
    {
        "name": "Global Billionaire #65",
        "netWorth": 78963066019.6779,
        "earningsPerSec": 175.27,
        "source": "Energy",
        "type": "Billionaire"
    },
    {
        "name": "Global Billionaire #84",
        "netWorth": 78952180789.58522,
        "earningsPerSec": 175.25,
        "source": "Real Estate",
        "type": "Billionaire"
    },
    {
        "name": "Global Billionaire #83",
        "netWorth": 78789192316.93246,
        "earningsPerSec": 174.89,
        "source": "Finance",
        "type": "Billionaire"
    },
    {
        "name": "Global Billionaire #122",
        "netWorth": 78345133621.41438,
        "earningsPerSec": 173.9,
        "source": "Energy",
        "type": "Billionaire"
    },
    {
        "name": "Global Billionaire #140",
        "netWorth": 77775722224.61407,
        "earningsPerSec": 172.64,
        "source": "Energy",
        "type": "Billionaire"
    },
    {
        "name": "Global Billionaire #66",
        "netWorth": 77535160811.94989,
        "earningsPerSec": 172.1,
        "source": "Finance",
        "type": "Billionaire"
    },
    {
        "name": "Global Billionaire #37",
        "netWorth": 77292655903.93533,
        "earningsPerSec": 171.57,
        "source": "Retail",
        "type": "Billionaire"
    },
    {
        "name": "Global Billionaire #112",
        "netWorth": 77136176802.53119,
        "earningsPerSec": 171.22,
        "source": "Energy",
        "type": "Billionaire"
    },
    {
        "name": "Global Billionaire #123",
        "netWorth": 76939940974.18982,
        "earningsPerSec": 170.78,
        "source": "Tech",
        "type": "Billionaire"
    },
    {
        "name": "Global Billionaire #77",
        "netWorth": 75204621809.12128,
        "earningsPerSec": 166.93,
        "source": "Retail",
        "type": "Billionaire"
    },
    {
        "name": "Global Billionaire #41",
        "netWorth": 74483016109.60242,
        "earningsPerSec": 165.33,
        "source": "Retail",
        "type": "Billionaire"
    },
    {
        "name": "Global Billionaire #142",
        "netWorth": 73894074235.45148,
        "earningsPerSec": 164.02,
        "source": "Tech",
        "type": "Billionaire"
    },
    {
        "name": "Global Billionaire #187",
        "netWorth": 73835507446.76974,
        "earningsPerSec": 163.89,
        "source": "Energy",
        "type": "Billionaire"
    },
    {
        "name": "Global Billionaire #42",
        "netWorth": 73198464375.40956,
        "earningsPerSec": 162.48,
        "source": "Finance",
        "type": "Billionaire"
    },
    {
        "name": "Global Billionaire #52",
        "netWorth": 72939092682.51537,
        "earningsPerSec": 161.9,
        "source": "Retail",
        "type": "Billionaire"
    },
    {
        "name": "Global Billionaire #40",
        "netWorth": 72105117127.74582,
        "earningsPerSec": 160.05,
        "source": "Tech",
        "type": "Billionaire"
    },
    {
        "name": "Global Billionaire #126",
        "netWorth": 70820132045.83907,
        "earningsPerSec": 157.2,
        "source": "Retail",
        "type": "Billionaire"
    },
    {
        "name": "Global Billionaire #188",
        "netWorth": 70789600632.51595,
        "earningsPerSec": 157.13,
        "source": "Finance",
        "type": "Billionaire"
    },
    {
        "name": "Global Billionaire #167",
        "netWorth": 70591503462.13739,
        "earningsPerSec": 156.69,
        "source": "Finance",
        "type": "Billionaire"
    },
    {
        "name": "Global Billionaire #157",
        "netWorth": 69381308070.49829,
        "earningsPerSec": 154.0,
        "source": "Energy",
        "type": "Billionaire"
    },
    {
        "name": "Global Billionaire #107",
        "netWorth": 68286541703.51444,
        "earningsPerSec": 151.57,
        "source": "Tech",
        "type": "Billionaire"
    },
    {
        "name": "Global Billionaire #138",
        "netWorth": 67680723995.18631,
        "earningsPerSec": 150.23,
        "source": "Real Estate",
        "type": "Billionaire"
    },
    {
        "name": "Global Billionaire #193",
        "netWorth": 67284080993.96941,
        "earningsPerSec": 149.35,
        "source": "Tech",
        "type": "Billionaire"
    },
    {
        "name": "Global Billionaire #33",
        "netWorth": 67280351816.10686,
        "earningsPerSec": 149.34,
        "source": "Retail",
        "type": "Billionaire"
    },
    {
        "name": "Global Billionaire #58",
        "netWorth": 67251428003.933075,
        "earningsPerSec": 149.28,
        "source": "Retail",
        "type": "Billionaire"
    },
    {
        "name": "Global Billionaire #30",
        "netWorth": 66476018686.77264,
        "earningsPerSec": 147.56,
        "source": "Retail",
        "type": "Billionaire"
    },
    {
        "name": "Global Billionaire #127",
        "netWorth": 65961889832.02687,
        "earningsPerSec": 146.41,
        "source": "Real Estate",
        "type": "Billionaire"
    },
    {
        "name": "Global Billionaire #55",
        "netWorth": 65890926144.8167,
        "earningsPerSec": 146.26,
        "source": "Finance",
        "type": "Billionaire"
    },
    {
        "name": "Global Billionaire #145",
        "netWorth": 64406345296.893394,
        "earningsPerSec": 142.96,
        "source": "Tech",
        "type": "Billionaire"
    },
    {
        "name": "Global Billionaire #168",
        "netWorth": 64186343508.789505,
        "earningsPerSec": 142.47,
        "source": "Retail",
        "type": "Billionaire"
    },
    {
        "name": "Global Billionaire #21",
        "netWorth": 63985674148.110725,
        "earningsPerSec": 142.03,
        "source": "Tech",
        "type": "Billionaire"
    },
    {
        "name": "Global Billionaire #74",
        "netWorth": 63708997544.45812,
        "earningsPerSec": 141.41,
        "source": "Tech",
        "type": "Billionaire"
    },
    {
        "name": "Global Billionaire #45",
        "netWorth": 63093246377.490585,
        "earningsPerSec": 140.05,
        "source": "Finance",
        "type": "Billionaire"
    },
    {
        "name": "Global Billionaire #164",
        "netWorth": 62827953846.14339,
        "earningsPerSec": 139.46,
        "source": "Real Estate",
        "type": "Billionaire"
    },
    {
        "name": "Global Billionaire #71",
        "netWorth": 62431891411.84559,
        "earningsPerSec": 138.58,
        "source": "Energy",
        "type": "Billionaire"
    },
    {
        "name": "Global Billionaire #114",
        "netWorth": 62180821382.04545,
        "earningsPerSec": 138.02,
        "source": "Tech",
        "type": "Billionaire"
    },
    {
        "name": "Global Billionaire #87",
        "netWorth": 61719698996.247765,
        "earningsPerSec": 137.0,
        "source": "Real Estate",
        "type": "Billionaire"
    },
    {
        "name": "Global Billionaire #57",
        "netWorth": 61383904824.21725,
        "earningsPerSec": 136.25,
        "source": "Finance",
        "type": "Billionaire"
    },
    {
        "name": "Global Billionaire #147",
        "netWorth": 60583242050.24466,
        "earningsPerSec": 134.48,
        "source": "Finance",
        "type": "Billionaire"
    },
    {
        "name": "Global Billionaire #81",
        "netWorth": 60318497800.95796,
        "earningsPerSec": 133.89,
        "source": "Energy",
        "type": "Billionaire"
    },
    {
        "name": "Global Billionaire #102",
        "netWorth": 60065127341.93032,
        "earningsPerSec": 133.33,
        "source": "Tech",
        "type": "Billionaire"
    },
    {
        "name": "Global Billionaire #131",
        "netWorth": 58800128481.794266,
        "earningsPerSec": 130.52,
        "source": "Finance",
        "type": "Billionaire"
    },
    {
        "name": "Global Billionaire #26",
        "netWorth": 58628115131.88198,
        "earningsPerSec": 130.14,
        "source": "Tech",
        "type": "Billionaire"
    },
    {
        "name": "Global Billionaire #174",
        "netWorth": 56621378732.18155,
        "earningsPerSec": 125.68,
        "source": "Finance",
        "type": "Billionaire"
    },
    {
        "name": "Global Billionaire #198",
        "netWorth": 56542264674.40253,
        "earningsPerSec": 125.51,
        "source": "Finance",
        "type": "Billionaire"
    },
    {
        "name": "Global Billionaire #93",
        "netWorth": 54916180025.4743,
        "earningsPerSec": 121.9,
        "source": "Retail",
        "type": "Billionaire"
    },
    {
        "name": "Global Billionaire #68",
        "netWorth": 54707711338.14365,
        "earningsPerSec": 121.43,
        "source": "Tech",
        "type": "Billionaire"
    },
    {
        "name": "Global Billionaire #183",
        "netWorth": 54606953696.38607,
        "earningsPerSec": 121.21,
        "source": "Energy",
        "type": "Billionaire"
    },
    {
        "name": "Global Billionaire #160",
        "netWorth": 53993617580.73335,
        "earningsPerSec": 119.85,
        "source": "Finance",
        "type": "Billionaire"
    },
    {
        "name": "Global Billionaire #48",
        "netWorth": 53841027143.72139,
        "earningsPerSec": 119.51,
        "source": "Finance",
        "type": "Billionaire"
    },
    {
        "name": "Global Billionaire #141",
        "netWorth": 52463333360.32049,
        "earningsPerSec": 116.45,
        "source": "Retail",
        "type": "Billionaire"
    },
    {
        "name": "Global Billionaire #143",
        "netWorth": 51905145590.26946,
        "earningsPerSec": 115.21,
        "source": "Finance",
        "type": "Billionaire"
    },
    {
        "name": "Global Billionaire #195",
        "netWorth": 51820114404.20742,
        "earningsPerSec": 115.02,
        "source": "Tech",
        "type": "Billionaire"
    },
    {
        "name": "Global Billionaire #34",
        "netWorth": 51503291776.30521,
        "earningsPerSec": 114.32,
        "source": "Retail",
        "type": "Billionaire"
    },
    {
        "name": "Global Billionaire #116",
        "netWorth": 51501819578.06207,
        "earningsPerSec": 114.32,
        "source": "Real Estate",
        "type": "Billionaire"
    },
    {
        "name": "Global Billionaire #149",
        "netWorth": 51448985077.19668,
        "earningsPerSec": 114.2,
        "source": "Finance",
        "type": "Billionaire"
    },
    {
        "name": "Global Billionaire #200",
        "netWorth": 50865502938.29226,
        "earningsPerSec": 112.91,
        "source": "Tech",
        "type": "Billionaire"
    },
    {
        "name": "Global Billionaire #49",
        "netWorth": 50470800819.31531,
        "earningsPerSec": 112.03,
        "source": "Retail",
        "type": "Billionaire"
    },
    {
        "name": "Global Billionaire #156",
        "netWorth": 50187992911.93254,
        "earningsPerSec": 111.4,
        "source": "Retail",
        "type": "Billionaire"
    },
    {
        "name": "Global Billionaire #189",
        "netWorth": 49941035805.12456,
        "earningsPerSec": 110.85,
        "source": "Tech",
        "type": "Billionaire"
    },
    {
        "name": "Global Billionaire #90",
        "netWorth": 48999930356.28099,
        "earningsPerSec": 108.76,
        "source": "Finance",
        "type": "Billionaire"
    },
    {
        "name": "Global Billionaire #170",
        "netWorth": 48381817202.229805,
        "earningsPerSec": 107.39,
        "source": "Finance",
        "type": "Billionaire"
    },
    {
        "name": "Global Billionaire #79",
        "netWorth": 48126103455.39891,
        "earningsPerSec": 106.82,
        "source": "Real Estate",
        "type": "Billionaire"
    },
    {
        "name": "Global Billionaire #98",
        "netWorth": 47829760067.0637,
        "earningsPerSec": 106.17,
        "source": "Real Estate",
        "type": "Billionaire"
    },
    {
        "name": "Global Billionaire #103",
        "netWorth": 47782394231.61965,
        "earningsPerSec": 106.06,
        "source": "Finance",
        "type": "Billionaire"
    },
    {
        "name": "Global Billionaire #186",
        "netWorth": 47258258380.68712,
        "earningsPerSec": 104.9,
        "source": "Tech",
        "type": "Billionaire"
    },
    {
        "name": "Global Billionaire #28",
        "netWorth": 44806697836.707405,
        "earningsPerSec": 99.46,
        "source": "Retail",
        "type": "Billionaire"
    },
    {
        "name": "Global Billionaire #182",
        "netWorth": 44724164897.3155,
        "earningsPerSec": 99.27,
        "source": "Energy",
        "type": "Billionaire"
    },
    {
        "name": "Global Billionaire #104",
        "netWorth": 44714786191.77944,
        "earningsPerSec": 99.25,
        "source": "Energy",
        "type": "Billionaire"
    },
    {
        "name": "Global Billionaire #96",
        "netWorth": 44083862870.69416,
        "earningsPerSec": 97.85,
        "source": "Real Estate",
        "type": "Billionaire"
    },
    {
        "name": "Global Billionaire #135",
        "netWorth": 43715639483.345116,
        "earningsPerSec": 97.03,
        "source": "Real Estate",
        "type": "Billionaire"
    },
    {
        "name": "Global Billionaire #101",
        "netWorth": 43409387863.641884,
        "earningsPerSec": 96.36,
        "source": "Real Estate",
        "type": "Billionaire"
    },
    {
        "name": "Global Billionaire #27",
        "netWorth": 43101155574.65381,
        "earningsPerSec": 95.67,
        "source": "Finance",
        "type": "Billionaire"
    },
    {
        "name": "Global Billionaire #158",
        "netWorth": 41618438674.633064,
        "earningsPerSec": 92.38,
        "source": "Real Estate",
        "type": "Billionaire"
    },
    {
        "name": "Global Billionaire #50",
        "netWorth": 40979157514.84245,
        "earningsPerSec": 90.96,
        "source": "Finance",
        "type": "Billionaire"
    },
    {
        "name": "Global Billionaire #62",
        "netWorth": 40759881478.60087,
        "earningsPerSec": 90.47,
        "source": "Tech",
        "type": "Billionaire"
    },
    {
        "name": "Global Billionaire #130",
        "netWorth": 40208143271.19208,
        "earningsPerSec": 89.25,
        "source": "Tech",
        "type": "Billionaire"
    },
    {
        "name": "Global Billionaire #137",
        "netWorth": 39941243782.43811,
        "earningsPerSec": 88.66,
        "source": "Energy",
        "type": "Billionaire"
    },
    {
        "name": "Global Billionaire #191",
        "netWorth": 39825353232.630325,
        "earningsPerSec": 88.4,
        "source": "Real Estate",
        "type": "Billionaire"
    },
    {
        "name": "Global Billionaire #199",
        "netWorth": 39517259493.92738,
        "earningsPerSec": 87.72,
        "source": "Real Estate",
        "type": "Billionaire"
    },
    {
        "name": "Global Billionaire #67",
        "netWorth": 39401259210.63612,
        "earningsPerSec": 87.46,
        "source": "Energy",
        "type": "Billionaire"
    },
    {
        "name": "Global Billionaire #113",
        "netWorth": 38482911329.729675,
        "earningsPerSec": 85.42,
        "source": "Energy",
        "type": "Billionaire"
    },
    {
        "name": "Global Billionaire #47",
        "netWorth": 37788875599.967705,
        "earningsPerSec": 83.88,
        "source": "Real Estate",
        "type": "Billionaire"
    },
    {
        "name": "Global Billionaire #197",
        "netWorth": 37615944307.6325,
        "earningsPerSec": 83.5,
        "source": "Energy",
        "type": "Billionaire"
    },
    {
        "name": "Global Billionaire #115",
        "netWorth": 36517277657.16177,
        "earningsPerSec": 81.06,
        "source": "Tech",
        "type": "Billionaire"
    },
    {
        "name": "Global Billionaire #56",
        "netWorth": 35724149192.66998,
        "earningsPerSec": 79.3,
        "source": "Retail",
        "type": "Billionaire"
    },
    {
        "name": "Global Billionaire #22",
        "netWorth": 35465290352.755165,
        "earningsPerSec": 78.72,
        "source": "Tech",
        "type": "Billionaire"
    },
    {
        "name": "Global Billionaire #134",
        "netWorth": 35102331908.852516,
        "earningsPerSec": 77.92,
        "source": "Energy",
        "type": "Billionaire"
    },
    {
        "name": "Global Billionaire #177",
        "netWorth": 34888349659.565025,
        "earningsPerSec": 77.44,
        "source": "Tech",
        "type": "Billionaire"
    },
    {
        "name": "Global Billionaire #144",
        "netWorth": 34545137710.9735,
        "earningsPerSec": 76.68,
        "source": "Tech",
        "type": "Billionaire"
    },
    {
        "name": "Global Billionaire #194",
        "netWorth": 34360972067.28722,
        "earningsPerSec": 76.27,
        "source": "Retail",
        "type": "Billionaire"
    },
    {
        "name": "Global Billionaire #64",
        "netWorth": 33400223201.06292,
        "earningsPerSec": 74.14,
        "source": "Retail",
        "type": "Billionaire"
    },
    {
        "name": "Global Billionaire #163",
        "netWorth": 33393313054.565716,
        "earningsPerSec": 74.12,
        "source": "Real Estate",
        "type": "Billionaire"
    },
    {
        "name": "Global Billionaire #46",
        "netWorth": 31894510282.613117,
        "earningsPerSec": 70.8,
        "source": "Real Estate",
        "type": "Billionaire"
    },
    {
        "name": "Global Billionaire #72",
        "netWorth": 30338014814.872128,
        "earningsPerSec": 67.34,
        "source": "Energy",
        "type": "Billionaire"
    },
    {
        "name": "Global Billionaire #136",
        "netWorth": 29803715479.75519,
        "earningsPerSec": 66.15,
        "source": "Energy",
        "type": "Billionaire"
    },
    {
        "name": "Global Billionaire #171",
        "netWorth": 29787731529.263676,
        "earningsPerSec": 66.12,
        "source": "Real Estate",
        "type": "Billionaire"
    },
    {
        "name": "Global Billionaire #155",
        "netWorth": 29771997673.76452,
        "earningsPerSec": 66.08,
        "source": "Tech",
        "type": "Billionaire"
    },
    {
        "name": "Global Billionaire #108",
        "netWorth": 29327689354.478,
        "earningsPerSec": 65.1,
        "source": "Energy",
        "type": "Billionaire"
    },
    {
        "name": "Global Billionaire #80",
        "netWorth": 29117011059.024784,
        "earningsPerSec": 64.63,
        "source": "Finance",
        "type": "Billionaire"
    },
    {
        "name": "Global Billionaire #129",
        "netWorth": 27474505461.615555,
        "earningsPerSec": 60.98,
        "source": "Retail",
        "type": "Billionaire"
    },
    {
        "name": "Global Billionaire #75",
        "netWorth": 27217089954.27084,
        "earningsPerSec": 60.41,
        "source": "Real Estate",
        "type": "Billionaire"
    },
    {
        "name": "Global Billionaire #73",
        "netWorth": 27082160009.556873,
        "earningsPerSec": 60.11,
        "source": "Retail",
        "type": "Billionaire"
    },
    {
        "name": "Global Billionaire #128",
        "netWorth": 26769326089.27149,
        "earningsPerSec": 59.42,
        "source": "Finance",
        "type": "Billionaire"
    },
    {
        "name": "Global Billionaire #35",
        "netWorth": 26569993645.14818,
        "earningsPerSec": 58.98,
        "source": "Finance",
        "type": "Billionaire"
    },
    {
        "name": "Global Billionaire #173",
        "netWorth": 25084459519.261997,
        "earningsPerSec": 55.68,
        "source": "Energy",
        "type": "Billionaire"
    },
    {
        "name": "Global Billionaire #97",
        "netWorth": 24638954212.505283,
        "earningsPerSec": 54.69,
        "source": "Retail",
        "type": "Billionaire"
    },
    {
        "name": "Global Billionaire #172",
        "netWorth": 23883310237.11787,
        "earningsPerSec": 53.01,
        "source": "Finance",
        "type": "Billionaire"
    },
    {
        "name": "Global Billionaire #38",
        "netWorth": 23606491794.727844,
        "earningsPerSec": 52.4,
        "source": "Real Estate",
        "type": "Billionaire"
    },
    {
        "name": "Global Billionaire #196",
        "netWorth": 22260329412.94772,
        "earningsPerSec": 49.41,
        "source": "Finance",
        "type": "Billionaire"
    },
    {
        "name": "Global Billionaire #78",
        "netWorth": 21727695176.85761,
        "earningsPerSec": 48.23,
        "source": "Real Estate",
        "type": "Billionaire"
    },
    {
        "name": "Global Billionaire #125",
        "netWorth": 21601268987.42166,
        "earningsPerSec": 47.95,
        "source": "Finance",
        "type": "Billionaire"
    },
    {
        "name": "Global Billionaire #53",
        "netWorth": 20517624089.314728,
        "earningsPerSec": 45.54,
        "source": "Tech",
        "type": "Billionaire"
    },
    {
        "name": "Global Billionaire #118",
        "netWorth": 19724343593.466576,
        "earningsPerSec": 43.78,
        "source": "Real Estate",
        "type": "Billionaire"
    },
    {
        "name": "Global Billionaire #54",
        "netWorth": 19295681910.472935,
        "earningsPerSec": 42.83,
        "source": "Energy",
        "type": "Billionaire"
    },
    {
        "name": "Global Billionaire #110",
        "netWorth": 19110870839.401382,
        "earningsPerSec": 42.42,
        "source": "Energy",
        "type": "Billionaire"
    },
    {
        "name": "Global Billionaire #91",
        "netWorth": 17911912367.146362,
        "earningsPerSec": 39.76,
        "source": "Finance",
        "type": "Billionaire"
    },
    {
        "name": "Global Billionaire #153",
        "netWorth": 17469286178.23024,
        "earningsPerSec": 38.78,
        "source": "Finance",
        "type": "Billionaire"
    },
    {
        "name": "Global Billionaire #124",
        "netWorth": 16517838365.378176,
        "earningsPerSec": 36.66,
        "source": "Real Estate",
        "type": "Billionaire"
    },
    {
        "name": "Global Billionaire #111",
        "netWorth": 16495065771.686018,
        "earningsPerSec": 36.61,
        "source": "Real Estate",
        "type": "Billionaire"
    },
    {
        "name": "Global Billionaire #117",
        "netWorth": 16320725701.730133,
        "earningsPerSec": 36.23,
        "source": "Energy",
        "type": "Billionaire"
    },
    {
        "name": "Global Billionaire #94",
        "netWorth": 15294295410.251184,
        "earningsPerSec": 33.95,
        "source": "Finance",
        "type": "Billionaire"
    },
    {
        "name": "Global Billionaire #109",
        "netWorth": 15067769252.295942,
        "earningsPerSec": 33.45,
        "source": "Finance",
        "type": "Billionaire"
    },
    {
        "name": "Global Billionaire #69",
        "netWorth": 14599971915.616072,
        "earningsPerSec": 32.41,
        "source": "Tech",
        "type": "Billionaire"
    },
    {
        "name": "Global Billionaire #148",
        "netWorth": 14007225387.596724,
        "earningsPerSec": 31.09,
        "source": "Energy",
        "type": "Billionaire"
    },
    {
        "name": "Global Billionaire #85",
        "netWorth": 12969230389.5522,
        "earningsPerSec": 28.79,
        "source": "Finance",
        "type": "Billionaire"
    },
    {
        "name": "Global Billionaire #89",
        "netWorth": 12447145512.859055,
        "earningsPerSec": 27.63,
        "source": "Retail",
        "type": "Billionaire"
    },
    {
        "name": "Global Billionaire #99",
        "netWorth": 11678554130.91236,
        "earningsPerSec": 25.92,
        "source": "Real Estate",
        "type": "Billionaire"
    },
    {
        "name": "Global Billionaire #39",
        "netWorth": 11249753509.903997,
        "earningsPerSec": 24.97,
        "source": "Finance",
        "type": "Billionaire"
    },
    {
        "name": "Global Billionaire #70",
        "netWorth": 11131304350.298388,
        "earningsPerSec": 24.71,
        "source": "Real Estate",
        "type": "Billionaire"
    },
    {
        "name": "Global Billionaire #161",
        "netWorth": 11077339369.732292,
        "earningsPerSec": 24.59,
        "source": "Retail",
        "type": "Billionaire"
    },
    {
        "name": "Global Billionaire #159",
        "netWorth": 11027018036.252026,
        "earningsPerSec": 24.48,
        "source": "Finance",
        "type": "Billionaire"
    },
    {
        "name": "Global Billionaire #139",
        "netWorth": 10405527451.966457,
        "earningsPerSec": 23.1,
        "source": "Real Estate",
        "type": "Billionaire"
    },
    {
        "name": "Global Billionaire #44",
        "netWorth": 10270747702.918762,
        "earningsPerSec": 22.8,
        "source": "Retail",
        "type": "Billionaire"
    },
    {
        "name": "Global Billionaire #152",
        "netWorth": 9665880430.500334,
        "earningsPerSec": 21.46,
        "source": "Tech",
        "type": "Billionaire"
    },
    {
        "name": "Global Billionaire #169",
        "netWorth": 8151373823.278856,
        "earningsPerSec": 18.09,
        "source": "Tech",
        "type": "Billionaire"
    },
    {
        "name": "Global Billionaire #150",
        "netWorth": 7936732336.445585,
        "earningsPerSec": 17.62,
        "source": "Energy",
        "type": "Billionaire"
    },
    {
        "name": "Global Billionaire #60",
        "netWorth": 7307931452.567673,
        "earningsPerSec": 16.22,
        "source": "Real Estate",
        "type": "Billionaire"
    },
    {
        "name": "Global Billionaire #51",
        "netWorth": 6664215242.885539,
        "earningsPerSec": 14.79,
        "source": "Energy",
        "type": "Billionaire"
    },
    {
        "name": "Global Billionaire #86",
        "netWorth": 6580917397.797432,
        "earningsPerSec": 14.61,
        "source": "Real Estate",
        "type": "Billionaire"
    },
    {
        "name": "Global Billionaire #88",
        "netWorth": 6480464043.976153,
        "earningsPerSec": 14.38,
        "source": "Energy",
        "type": "Billionaire"
    },
    {
        "name": "Global Billionaire #36",
        "netWorth": 6358050705.03202,
        "earningsPerSec": 14.11,
        "source": "Tech",
        "type": "Billionaire"
    },
    {
        "name": "Global Billionaire #185",
        "netWorth": 6029625582.0552025,
        "earningsPerSec": 13.38,
        "source": "Energy",
        "type": "Billionaire"
    },
    {
        "name": "Global Billionaire #175",
        "netWorth": 5753243405.897725,
        "earningsPerSec": 12.77,
        "source": "Retail",
        "type": "Billionaire"
    },
    {
        "name": "Global Billionaire #151",
        "netWorth": 5603548554.376365,
        "earningsPerSec": 12.44,
        "source": "Real Estate",
        "type": "Billionaire"
    },
    {
        "name": "Global Billionaire #180",
        "netWorth": 5374044823.497753,
        "earningsPerSec": 11.93,
        "source": "Retail",
        "type": "Billionaire"
    },
    {
        "name": "Global Billionaire #24",
        "netWorth": 4974608205.602827,
        "earningsPerSec": 11.04,
        "source": "Finance",
        "type": "Billionaire"
    },
    {
        "name": "Global Billionaire #119",
        "netWorth": 4528753004.90131,
        "earningsPerSec": 10.05,
        "source": "Real Estate",
        "type": "Billionaire"
    },
    {
        "name": "Global Billionaire #121",
        "netWorth": 4264623693.348233,
        "earningsPerSec": 9.47,
        "source": "Energy",
        "type": "Billionaire"
    },
    {
        "name": "Global Billionaire #59",
        "netWorth": 3709434911.243943,
        "earningsPerSec": 8.23,
        "source": "Real Estate",
        "type": "Billionaire"
    },
    {
        "name": "Global Billionaire #25",
        "netWorth": 3463821434.1486387,
        "earningsPerSec": 7.69,
        "source": "Real Estate",
        "type": "Billionaire"
    },
    {
        "name": "Global Billionaire #31",
        "netWorth": 3113647640.500583,
        "earningsPerSec": 6.91,
        "source": "Finance",
        "type": "Billionaire"
    },
    {
        "name": "Global Billionaire #176",
        "netWorth": 3026179457.7419376,
        "earningsPerSec": 6.72,
        "source": "Tech",
        "type": "Billionaire"
    },
    {
        "name": "Jay-Z",
        "netWorth": 2500000000.0,
        "earningsPerSec": 15.85,
        "source": "Music",
        "type": "Celebrity"
    },
    {
        "name": "Kim Kardashian",
        "netWorth": 1700000000.0,
        "earningsPerSec": 10.78,
        "source": "Business",
        "type": "Celebrity"
    },
    {
        "name": "Global Billionaire #165",
        "netWorth": 1400961035.3522341,
        "earningsPerSec": 3.11,
        "source": "Retail",
        "type": "Billionaire"
    },
    {
        "name": "Rihanna",
        "netWorth": 1400000000.0,
        "earningsPerSec": 8.88,
        "source": "Music",
        "type": "Celebrity"
    },
    {
        "name": "Taylor Swift",
        "netWorth": 1200000000.0,
        "earningsPerSec": 7.61,
        "source": "Music",
        "type": "Celebrity"
    },
    {
        "name": "LeBron James",
        "netWorth": 1200000000.0,
        "earningsPerSec": 7.61,
        "source": "Sports",
        "type": "Celebrity"
    },
    {
        "name": "Tiger Woods",
        "netWorth": 1100000000.0,
        "earningsPerSec": 6.98,
        "source": "Sports",
        "type": "Celebrity"
    },
    {
        "name": "Global Billionaire #105",
        "netWorth": 1047920652.5935522,
        "earningsPerSec": 2.33,
        "source": "Energy",
        "type": "Billionaire"
    },
    {
        "name": "Top Influencer #175",
        "netWorth": 899512323.5556659,
        "earningsPerSec": 4.28,
        "source": "Influencer",
        "type": "Celebrity"
    },
    {
        "name": "Top Influencer #101",
        "netWorth": 894425498.4502057,
        "earningsPerSec": 4.25,
        "source": "Influencer",
        "type": "Celebrity"
    },
    {
        "name": "Top Actor #187",
        "netWorth": 880670395.3348761,
        "earningsPerSec": 4.19,
        "source": "Actor",
        "type": "Celebrity"
    },
    {
        "name": "Top Actor #157",
        "netWorth": 877573738.8563478,
        "earningsPerSec": 4.17,
        "source": "Actor",
        "type": "Celebrity"
    },
    {
        "name": "Top Actor #112",
        "netWorth": 874817197.2609904,
        "earningsPerSec": 4.16,
        "source": "Actor",
        "type": "Celebrity"
    },
    {
        "name": "Top Singer #180",
        "netWorth": 871074205.0295714,
        "earningsPerSec": 4.14,
        "source": "Singer",
        "type": "Celebrity"
    },
    {
        "name": "Top Athlete #34",
        "netWorth": 847592415.3464988,
        "earningsPerSec": 4.03,
        "source": "Athlete",
        "type": "Celebrity"
    },
    {
        "name": "Top Athlete #103",
        "netWorth": 844350309.3013064,
        "earningsPerSec": 4.02,
        "source": "Athlete",
        "type": "Celebrity"
    },
    {
        "name": "Top Singer #143",
        "netWorth": 843477894.3634931,
        "earningsPerSec": 4.01,
        "source": "Singer",
        "type": "Celebrity"
    },
    {
        "name": "Top Influencer #160",
        "netWorth": 838607388.7969077,
        "earningsPerSec": 3.99,
        "source": "Influencer",
        "type": "Celebrity"
    },
    {
        "name": "Top Director #53",
        "netWorth": 832939784.7578145,
        "earningsPerSec": 3.96,
        "source": "Director",
        "type": "Celebrity"
    },
    {
        "name": "Top Singer #189",
        "netWorth": 831890299.7408357,
        "earningsPerSec": 3.96,
        "source": "Singer",
        "type": "Celebrity"
    },
    {
        "name": "Top Influencer #123",
        "netWorth": 830398890.7251325,
        "earningsPerSec": 3.95,
        "source": "Influencer",
        "type": "Celebrity"
    },
    {
        "name": "Top Influencer #45",
        "netWorth": 819748039.3278611,
        "earningsPerSec": 3.9,
        "source": "Influencer",
        "type": "Celebrity"
    },
    {
        "name": "Top Influencer #198",
        "netWorth": 819272226.9220426,
        "earningsPerSec": 3.9,
        "source": "Influencer",
        "type": "Celebrity"
    },
    {
        "name": "Top Singer #52",
        "netWorth": 808702952.9737346,
        "earningsPerSec": 3.85,
        "source": "Singer",
        "type": "Celebrity"
    },
    {
        "name": "Top Singer #50",
        "netWorth": 805115226.3313627,
        "earningsPerSec": 3.83,
        "source": "Singer",
        "type": "Celebrity"
    },
    {
        "name": "Cristiano Ronaldo",
        "netWorth": 800000000.0,
        "earningsPerSec": 5.07,
        "source": "Sports",
        "type": "Celebrity"
    },
    {
        "name": "Dwayne Johnson",
        "netWorth": 800000000.0,
        "earningsPerSec": 5.07,
        "source": "Movies",
        "type": "Celebrity"
    },
    {
        "name": "Top Influencer #78",
        "netWorth": 798527042.4223772,
        "earningsPerSec": 3.8,
        "source": "Influencer",
        "type": "Celebrity"
    },
    {
        "name": "Top Director #99",
        "netWorth": 798128488.6651514,
        "earningsPerSec": 3.8,
        "source": "Director",
        "type": "Celebrity"
    },
    {
        "name": "Top Athlete #133",
        "netWorth": 792626753.4679528,
        "earningsPerSec": 3.77,
        "source": "Athlete",
        "type": "Celebrity"
    },
    {
        "name": "Top Director #26",
        "netWorth": 790938869.4367436,
        "earningsPerSec": 3.76,
        "source": "Director",
        "type": "Celebrity"
    },
    {
        "name": "Top Actor #195",
        "netWorth": 789242293.3092549,
        "earningsPerSec": 3.75,
        "source": "Actor",
        "type": "Celebrity"
    },
    {
        "name": "Top Influencer #82",
        "netWorth": 783047410.7799889,
        "earningsPerSec": 3.72,
        "source": "Influencer",
        "type": "Celebrity"
    },
    {
        "name": "Top Influencer #27",
        "netWorth": 780031457.9262329,
        "earningsPerSec": 3.71,
        "source": "Influencer",
        "type": "Celebrity"
    },
    {
        "name": "Top Influencer #185",
        "netWorth": 774357264.2705752,
        "earningsPerSec": 3.68,
        "source": "Influencer",
        "type": "Celebrity"
    },
    {
        "name": "Top Athlete #151",
        "netWorth": 771852960.7852098,
        "earningsPerSec": 3.67,
        "source": "Athlete",
        "type": "Celebrity"
    },
    {
        "name": "Top Influencer #75",
        "netWorth": 769343442.4758139,
        "earningsPerSec": 3.66,
        "source": "Influencer",
        "type": "Celebrity"
    },
    {
        "name": "Top Singer #36",
        "netWorth": 764808149.817105,
        "earningsPerSec": 3.64,
        "source": "Singer",
        "type": "Celebrity"
    },
    {
        "name": "Top Singer #197",
        "netWorth": 760678643.0005609,
        "earningsPerSec": 3.62,
        "source": "Singer",
        "type": "Celebrity"
    },
    {
        "name": "Top Influencer #49",
        "netWorth": 758298538.1257364,
        "earningsPerSec": 3.61,
        "source": "Influencer",
        "type": "Celebrity"
    },
    {
        "name": "Top Director #132",
        "netWorth": 754849045.9184184,
        "earningsPerSec": 3.59,
        "source": "Director",
        "type": "Celebrity"
    },
    {
        "name": "Top Singer #148",
        "netWorth": 751899899.0420794,
        "earningsPerSec": 3.58,
        "source": "Singer",
        "type": "Celebrity"
    },
    {
        "name": "Kylie Jenner",
        "netWorth": 750000000.0,
        "earningsPerSec": 4.76,
        "source": "Cosmetics",
        "type": "Celebrity"
    },
    {
        "name": "Top Singer #165",
        "netWorth": 742342649.6805041,
        "earningsPerSec": 3.53,
        "source": "Singer",
        "type": "Celebrity"
    },
    {
        "name": "Top Director #156",
        "netWorth": 734292502.4320587,
        "earningsPerSec": 3.49,
        "source": "Director",
        "type": "Celebrity"
    },
    {
        "name": "Top Influencer #127",
        "netWorth": 732625983.267418,
        "earningsPerSec": 3.48,
        "source": "Influencer",
        "type": "Celebrity"
    },
    {
        "name": "Top Actor #79",
        "netWorth": 720350979.8659579,
        "earningsPerSec": 3.43,
        "source": "Actor",
        "type": "Celebrity"
    },
    {
        "name": "Top Actor #154",
        "netWorth": 720063973.1799781,
        "earningsPerSec": 3.42,
        "source": "Actor",
        "type": "Celebrity"
    },
    {
        "name": "Top Influencer #87",
        "netWorth": 717437726.8761431,
        "earningsPerSec": 3.41,
        "source": "Influencer",
        "type": "Celebrity"
    },
    {
        "name": "Top Influencer #196",
        "netWorth": 712030253.9266573,
        "earningsPerSec": 3.39,
        "source": "Influencer",
        "type": "Celebrity"
    },
    {
        "name": "Top Actor #33",
        "netWorth": 707020319.7140193,
        "earningsPerSec": 3.36,
        "source": "Actor",
        "type": "Celebrity"
    },
    {
        "name": "Top Actor #191",
        "netWorth": 702247440.6016197,
        "earningsPerSec": 3.34,
        "source": "Actor",
        "type": "Celebrity"
    },
    {
        "name": "Top Singer #80",
        "netWorth": 701134749.6386046,
        "earningsPerSec": 3.33,
        "source": "Singer",
        "type": "Celebrity"
    },
    {
        "name": "Top Actor #135",
        "netWorth": 690167605.7533064,
        "earningsPerSec": 3.28,
        "source": "Actor",
        "type": "Celebrity"
    },
    {
        "name": "Top Director #93",
        "netWorth": 688072035.3960572,
        "earningsPerSec": 3.27,
        "source": "Director",
        "type": "Celebrity"
    },
    {
        "name": "Top Actor #134",
        "netWorth": 672771696.0395745,
        "earningsPerSec": 3.2,
        "source": "Actor",
        "type": "Celebrity"
    },
    {
        "name": "Top Director #115",
        "netWorth": 670455288.5572772,
        "earningsPerSec": 3.19,
        "source": "Director",
        "type": "Celebrity"
    },
    {
        "name": "Top Influencer #176",
        "netWorth": 665052465.751281,
        "earningsPerSec": 3.16,
        "source": "Influencer",
        "type": "Celebrity"
    },
    {
        "name": "Top Singer #106",
        "netWorth": 657314034.0204363,
        "earningsPerSec": 3.13,
        "source": "Singer",
        "type": "Celebrity"
    },
    {
        "name": "Top Actor #116",
        "netWorth": 655231418.9507511,
        "earningsPerSec": 3.12,
        "source": "Actor",
        "type": "Celebrity"
    },
    {
        "name": "Lionel Messi",
        "netWorth": 650000000.0,
        "earningsPerSec": 4.12,
        "source": "Sports",
        "type": "Celebrity"
    },
    {
        "name": "Top Singer #102",
        "netWorth": 645576324.6733962,
        "earningsPerSec": 3.07,
        "source": "Singer",
        "type": "Celebrity"
    },
    {
        "name": "Top Director #76",
        "netWorth": 638069512.9134299,
        "earningsPerSec": 3.03,
        "source": "Director",
        "type": "Celebrity"
    },
    {
        "name": "Top Director #77",
        "netWorth": 636204036.6439836,
        "earningsPerSec": 3.03,
        "source": "Director",
        "type": "Celebrity"
    },
    {
        "name": "Top Singer #40",
        "netWorth": 628796026.7336618,
        "earningsPerSec": 2.99,
        "source": "Singer",
        "type": "Celebrity"
    },
    {
        "name": "Top Athlete #88",
        "netWorth": 617671337.7360353,
        "earningsPerSec": 2.94,
        "source": "Athlete",
        "type": "Celebrity"
    },
    {
        "name": "Top Influencer #69",
        "netWorth": 613882540.2351712,
        "earningsPerSec": 2.92,
        "source": "Influencer",
        "type": "Celebrity"
    },
    {
        "name": "Top Influencer #158",
        "netWorth": 600586668.4403371,
        "earningsPerSec": 2.86,
        "source": "Influencer",
        "type": "Celebrity"
    },
    {
        "name": "Tom Cruise",
        "netWorth": 600000000.0,
        "earningsPerSec": 3.81,
        "source": "Movies",
        "type": "Celebrity"
    },
    {
        "name": "Top Singer #109",
        "netWorth": 595974801.5057923,
        "earningsPerSec": 2.83,
        "source": "Singer",
        "type": "Celebrity"
    },
    {
        "name": "Top Director #119",
        "netWorth": 590646551.2722647,
        "earningsPerSec": 2.81,
        "source": "Director",
        "type": "Celebrity"
    },
    {
        "name": "Top Singer #104",
        "netWorth": 580761042.6385092,
        "earningsPerSec": 2.76,
        "source": "Singer",
        "type": "Celebrity"
    },
    {
        "name": "Top Actor #85",
        "netWorth": 579634611.1057343,
        "earningsPerSec": 2.76,
        "source": "Actor",
        "type": "Celebrity"
    },
    {
        "name": "Top Director #71",
        "netWorth": 577928079.3960483,
        "earningsPerSec": 2.75,
        "source": "Director",
        "type": "Celebrity"
    },
    {
        "name": "Top Athlete #98",
        "netWorth": 577371393.5853027,
        "earningsPerSec": 2.75,
        "source": "Athlete",
        "type": "Celebrity"
    },
    {
        "name": "Top Athlete #177",
        "netWorth": 573542261.2349532,
        "earningsPerSec": 2.73,
        "source": "Athlete",
        "type": "Celebrity"
    },
    {
        "name": "Top Singer #32",
        "netWorth": 568183403.8377035,
        "earningsPerSec": 2.7,
        "source": "Singer",
        "type": "Celebrity"
    },
    {
        "name": "Top Athlete #170",
        "netWorth": 561457270.8534125,
        "earningsPerSec": 2.67,
        "source": "Athlete",
        "type": "Celebrity"
    },
    {
        "name": "Top Singer #124",
        "netWorth": 550979159.2752448,
        "earningsPerSec": 2.62,
        "source": "Singer",
        "type": "Celebrity"
    },
    {
        "name": "Top Actor #155",
        "netWorth": 547505091.0772117,
        "earningsPerSec": 2.6,
        "source": "Actor",
        "type": "Celebrity"
    },
    {
        "name": "Top Athlete #137",
        "netWorth": 546702148.5035539,
        "earningsPerSec": 2.6,
        "source": "Athlete",
        "type": "Celebrity"
    },
    {
        "name": "Top Director #174",
        "netWorth": 541970863.0174187,
        "earningsPerSec": 2.58,
        "source": "Director",
        "type": "Celebrity"
    },
    {
        "name": "Top Actor #96",
        "netWorth": 514529855.3623284,
        "earningsPerSec": 2.45,
        "source": "Actor",
        "type": "Celebrity"
    },
    {
        "name": "Top Influencer #21",
        "netWorth": 507819085.62125343,
        "earningsPerSec": 2.42,
        "source": "Influencer",
        "type": "Celebrity"
    },
    {
        "name": "MrBeast",
        "netWorth": 500000000.0,
        "earningsPerSec": 3.17,
        "source": "YouTube",
        "type": "Celebrity"
    },
    {
        "name": "Top Actor #178",
        "netWorth": 488739916.84080446,
        "earningsPerSec": 2.32,
        "source": "Actor",
        "type": "Celebrity"
    },
    {
        "name": "Top Athlete #181",
        "netWorth": 485642667.464422,
        "earningsPerSec": 2.31,
        "source": "Athlete",
        "type": "Celebrity"
    },
    {
        "name": "Top Director #92",
        "netWorth": 482077830.3749935,
        "earningsPerSec": 2.29,
        "source": "Director",
        "type": "Celebrity"
    },
    {
        "name": "Top Athlete #162",
        "netWorth": 481289431.0596893,
        "earningsPerSec": 2.29,
        "source": "Athlete",
        "type": "Celebrity"
    },
    {
        "name": "Top Athlete #144",
        "netWorth": 468221341.55570763,
        "earningsPerSec": 2.23,
        "source": "Athlete",
        "type": "Celebrity"
    },
    {
        "name": "Top Athlete #121",
        "netWorth": 462699187.9061564,
        "earningsPerSec": 2.2,
        "source": "Athlete",
        "type": "Celebrity"
    },
    {
        "name": "Top Director #139",
        "netWorth": 460819611.3116949,
        "earningsPerSec": 2.19,
        "source": "Director",
        "type": "Celebrity"
    },
    {
        "name": "Top Singer #168",
        "netWorth": 460557311.87251234,
        "earningsPerSec": 2.19,
        "source": "Singer",
        "type": "Celebrity"
    },
    {
        "name": "Top Director #184",
        "netWorth": 457888290.9521535,
        "earningsPerSec": 2.18,
        "source": "Director",
        "type": "Celebrity"
    },
    {
        "name": "Top Athlete #28",
        "netWorth": 455029999.33671707,
        "earningsPerSec": 2.16,
        "source": "Athlete",
        "type": "Celebrity"
    },
    {
        "name": "Top Singer #30",
        "netWorth": 449611109.1652851,
        "earningsPerSec": 2.14,
        "source": "Singer",
        "type": "Celebrity"
    },
    {
        "name": "Top Athlete #111",
        "netWorth": 449472777.0233271,
        "earningsPerSec": 2.14,
        "source": "Athlete",
        "type": "Celebrity"
    },
    {
        "name": "Top Singer #57",
        "netWorth": 447040713.7362999,
        "earningsPerSec": 2.13,
        "source": "Singer",
        "type": "Celebrity"
    },
    {
        "name": "Top Singer #188",
        "netWorth": 446646678.005236,
        "earningsPerSec": 2.12,
        "source": "Singer",
        "type": "Celebrity"
    },
    {
        "name": "Top Singer #43",
        "netWorth": 445347223.05737144,
        "earningsPerSec": 2.12,
        "source": "Singer",
        "type": "Celebrity"
    },
    {
        "name": "Top Actor #67",
        "netWorth": 443908908.09955466,
        "earningsPerSec": 2.11,
        "source": "Actor",
        "type": "Celebrity"
    },
    {
        "name": "Top Athlete #63",
        "netWorth": 441454284.1601828,
        "earningsPerSec": 2.1,
        "source": "Athlete",
        "type": "Celebrity"
    },
    {
        "name": "Top Athlete #193",
        "netWorth": 438216051.3851118,
        "earningsPerSec": 2.08,
        "source": "Athlete",
        "type": "Celebrity"
    },
    {
        "name": "Top Singer #169",
        "netWorth": 437958780.6434601,
        "earningsPerSec": 2.08,
        "source": "Singer",
        "type": "Celebrity"
    },
    {
        "name": "Top Singer #138",
        "netWorth": 433971982.3341121,
        "earningsPerSec": 2.06,
        "source": "Singer",
        "type": "Celebrity"
    },
    {
        "name": "Top Director #182",
        "netWorth": 429651736.1884515,
        "earningsPerSec": 2.04,
        "source": "Director",
        "type": "Celebrity"
    },
    {
        "name": "Top Influencer #60",
        "netWorth": 427641560.7348037,
        "earningsPerSec": 2.03,
        "source": "Influencer",
        "type": "Celebrity"
    },
    {
        "name": "Top Actor #172",
        "netWorth": 423098252.49981093,
        "earningsPerSec": 2.01,
        "source": "Actor",
        "type": "Celebrity"
    },
    {
        "name": "Top Singer #167",
        "netWorth": 419178554.557924,
        "earningsPerSec": 1.99,
        "source": "Singer",
        "type": "Celebrity"
    },
    {
        "name": "Top Actor #100",
        "netWorth": 414971744.0113848,
        "earningsPerSec": 1.97,
        "source": "Actor",
        "type": "Celebrity"
    },
    {
        "name": "Top Singer #200",
        "netWorth": 414827801.1421188,
        "earningsPerSec": 1.97,
        "source": "Singer",
        "type": "Celebrity"
    },
    {
        "name": "Top Singer #128",
        "netWorth": 410304380.3912784,
        "earningsPerSec": 1.95,
        "source": "Singer",
        "type": "Celebrity"
    },
    {
        "name": "Top Singer #22",
        "netWorth": 408857053.17825365,
        "earningsPerSec": 1.94,
        "source": "Singer",
        "type": "Celebrity"
    },
    {
        "name": "Top Actor #65",
        "netWorth": 395544513.06139684,
        "earningsPerSec": 1.88,
        "source": "Actor",
        "type": "Celebrity"
    },
    {
        "name": "Top Influencer #131",
        "netWorth": 387297645.984076,
        "earningsPerSec": 1.84,
        "source": "Influencer",
        "type": "Celebrity"
    },
    {
        "name": "Top Director #83",
        "netWorth": 384898566.6794579,
        "earningsPerSec": 1.83,
        "source": "Director",
        "type": "Celebrity"
    },
    {
        "name": "Top Actor #126",
        "netWorth": 373261691.1096493,
        "earningsPerSec": 1.78,
        "source": "Actor",
        "type": "Celebrity"
    },
    {
        "name": "Top Influencer #68",
        "netWorth": 359545427.5416612,
        "earningsPerSec": 1.71,
        "source": "Influencer",
        "type": "Celebrity"
    },
    {
        "name": "Top Athlete #190",
        "netWorth": 356870728.2723922,
        "earningsPerSec": 1.7,
        "source": "Athlete",
        "type": "Celebrity"
    },
    {
        "name": "Top Singer #23",
        "netWorth": 347633460.56481564,
        "earningsPerSec": 1.65,
        "source": "Singer",
        "type": "Celebrity"
    },
    {
        "name": "Top Athlete #62",
        "netWorth": 340299487.3000497,
        "earningsPerSec": 1.62,
        "source": "Athlete",
        "type": "Celebrity"
    },
    {
        "name": "Top Athlete #72",
        "netWorth": 333078284.2663548,
        "earningsPerSec": 1.58,
        "source": "Athlete",
        "type": "Celebrity"
    },
    {
        "name": "Top Influencer #73",
        "netWorth": 324490484.2360647,
        "earningsPerSec": 1.54,
        "source": "Influencer",
        "type": "Celebrity"
    },
    {
        "name": "Top Athlete #84",
        "netWorth": 323213629.88005984,
        "earningsPerSec": 1.54,
        "source": "Athlete",
        "type": "Celebrity"
    },
    {
        "name": "Top Athlete #125",
        "netWorth": 316034169.54828435,
        "earningsPerSec": 1.5,
        "source": "Athlete",
        "type": "Celebrity"
    },
    {
        "name": "Top Singer #35",
        "netWorth": 313534745.1495014,
        "earningsPerSec": 1.49,
        "source": "Singer",
        "type": "Celebrity"
    },
    {
        "name": "Top Influencer #25",
        "netWorth": 304614000.9647713,
        "earningsPerSec": 1.45,
        "source": "Influencer",
        "type": "Celebrity"
    },
    {
        "name": "Top Actor #97",
        "netWorth": 300918520.42132795,
        "earningsPerSec": 1.43,
        "source": "Actor",
        "type": "Celebrity"
    },
    {
        "name": "Top Singer #56",
        "netWorth": 300737507.5764316,
        "earningsPerSec": 1.43,
        "source": "Singer",
        "type": "Celebrity"
    },
    {
        "name": "Top Athlete #46",
        "netWorth": 293469499.4477527,
        "earningsPerSec": 1.4,
        "source": "Athlete",
        "type": "Celebrity"
    },
    {
        "name": "Top Actor #90",
        "netWorth": 292800606.79917693,
        "earningsPerSec": 1.39,
        "source": "Actor",
        "type": "Celebrity"
    },
    {
        "name": "Top Influencer #81",
        "netWorth": 290926990.3661121,
        "earningsPerSec": 1.38,
        "source": "Influencer",
        "type": "Celebrity"
    },
    {
        "name": "Top Influencer #113",
        "netWorth": 281651165.55721056,
        "earningsPerSec": 1.34,
        "source": "Influencer",
        "type": "Celebrity"
    },
    {
        "name": "Top Influencer #171",
        "netWorth": 278310805.40385383,
        "earningsPerSec": 1.32,
        "source": "Influencer",
        "type": "Celebrity"
    },
    {
        "name": "Top Actor #136",
        "netWorth": 273645426.47499293,
        "earningsPerSec": 1.3,
        "source": "Actor",
        "type": "Celebrity"
    },
    {
        "name": "Top Influencer #24",
        "netWorth": 269861785.2816981,
        "earningsPerSec": 1.28,
        "source": "Influencer",
        "type": "Celebrity"
    },
    {
        "name": "Top Athlete #37",
        "netWorth": 264124275.40368623,
        "earningsPerSec": 1.26,
        "source": "Athlete",
        "type": "Celebrity"
    },
    {
        "name": "Top Actor #142",
        "netWorth": 263438744.09696543,
        "earningsPerSec": 1.25,
        "source": "Actor",
        "type": "Celebrity"
    },
    {
        "name": "Top Singer #95",
        "netWorth": 254076440.51028427,
        "earningsPerSec": 1.21,
        "source": "Singer",
        "type": "Celebrity"
    },
    {
        "name": "Top Athlete #192",
        "netWorth": 252708228.95439637,
        "earningsPerSec": 1.2,
        "source": "Athlete",
        "type": "Celebrity"
    },
    {
        "name": "Eminem",
        "netWorth": 250000000.0,
        "earningsPerSec": 1.59,
        "source": "Music",
        "type": "Celebrity"
    },
    {
        "name": "Top Actor #58",
        "netWorth": 249943981.5145758,
        "earningsPerSec": 1.19,
        "source": "Actor",
        "type": "Celebrity"
    },
    {
        "name": "Top Athlete #110",
        "netWorth": 243270025.9172324,
        "earningsPerSec": 1.16,
        "source": "Athlete",
        "type": "Celebrity"
    },
    {
        "name": "Top Director #141",
        "netWorth": 239682735.10412502,
        "earningsPerSec": 1.14,
        "source": "Director",
        "type": "Celebrity"
    },
    {
        "name": "Top Actor #86",
        "netWorth": 225056488.6897731,
        "earningsPerSec": 1.07,
        "source": "Actor",
        "type": "Celebrity"
    },
    {
        "name": "Top Actor #61",
        "netWorth": 214918259.65333068,
        "earningsPerSec": 1.02,
        "source": "Actor",
        "type": "Celebrity"
    },
    {
        "name": "Top Actor #64",
        "netWorth": 213989719.82653835,
        "earningsPerSec": 1.02,
        "source": "Actor",
        "type": "Celebrity"
    },
    {
        "name": "Top Singer #149",
        "netWorth": 205022130.40515265,
        "earningsPerSec": 0.98,
        "source": "Singer",
        "type": "Celebrity"
    },
    {
        "name": "Top Athlete #150",
        "netWorth": 204359114.85714284,
        "earningsPerSec": 0.97,
        "source": "Athlete",
        "type": "Celebrity"
    },
    {
        "name": "Top Singer #140",
        "netWorth": 201924699.42263985,
        "earningsPerSec": 0.96,
        "source": "Singer",
        "type": "Celebrity"
    },
    {
        "name": "Top Singer #173",
        "netWorth": 195605470.5354783,
        "earningsPerSec": 0.93,
        "source": "Singer",
        "type": "Celebrity"
    },
    {
        "name": "Top Athlete #129",
        "netWorth": 194492948.19594675,
        "earningsPerSec": 0.93,
        "source": "Athlete",
        "type": "Celebrity"
    },
    {
        "name": "Top Director #108",
        "netWorth": 190705135.566544,
        "earningsPerSec": 0.91,
        "source": "Director",
        "type": "Celebrity"
    },
    {
        "name": "Top Actor #89",
        "netWorth": 187820109.79872084,
        "earningsPerSec": 0.89,
        "source": "Actor",
        "type": "Celebrity"
    },
    {
        "name": "Top Athlete #39",
        "netWorth": 181209453.17963734,
        "earningsPerSec": 0.86,
        "source": "Athlete",
        "type": "Celebrity"
    },
    {
        "name": "Top Singer #59",
        "netWorth": 180586499.44702342,
        "earningsPerSec": 0.86,
        "source": "Singer",
        "type": "Celebrity"
    },
    {
        "name": "Top Singer #55",
        "netWorth": 178588871.4406734,
        "earningsPerSec": 0.85,
        "source": "Singer",
        "type": "Celebrity"
    },
    {
        "name": "Top Director #122",
        "netWorth": 173358571.18458965,
        "earningsPerSec": 0.82,
        "source": "Director",
        "type": "Celebrity"
    },
    {
        "name": "Top Director #105",
        "netWorth": 172681490.43880856,
        "earningsPerSec": 0.82,
        "source": "Director",
        "type": "Celebrity"
    },
    {
        "name": "Top Athlete #163",
        "netWorth": 161615716.0860111,
        "earningsPerSec": 0.77,
        "source": "Athlete",
        "type": "Celebrity"
    },
    {
        "name": "Top Director #66",
        "netWorth": 161595755.35699952,
        "earningsPerSec": 0.77,
        "source": "Director",
        "type": "Celebrity"
    },
    {
        "name": "Top Athlete #161",
        "netWorth": 157625524.5047746,
        "earningsPerSec": 0.75,
        "source": "Athlete",
        "type": "Celebrity"
    },
    {
        "name": "Top Actor #51",
        "netWorth": 151404151.32528034,
        "earningsPerSec": 0.72,
        "source": "Actor",
        "type": "Celebrity"
    },
    {
        "name": "Top Influencer #146",
        "netWorth": 148950691.3687826,
        "earningsPerSec": 0.71,
        "source": "Influencer",
        "type": "Celebrity"
    },
    {
        "name": "Top Director #117",
        "netWorth": 145197473.12625343,
        "earningsPerSec": 0.69,
        "source": "Director",
        "type": "Celebrity"
    },
    {
        "name": "Top Influencer #199",
        "netWorth": 129446210.50428626,
        "earningsPerSec": 0.62,
        "source": "Influencer",
        "type": "Celebrity"
    },
    {
        "name": "Top Director #54",
        "netWorth": 128288249.56841905,
        "earningsPerSec": 0.61,
        "source": "Director",
        "type": "Celebrity"
    },
    {
        "name": "Top Athlete #114",
        "netWorth": 127457851.76681787,
        "earningsPerSec": 0.61,
        "source": "Athlete",
        "type": "Celebrity"
    },
    {
        "name": "Top Influencer #48",
        "netWorth": 121530511.77908047,
        "earningsPerSec": 0.58,
        "source": "Influencer",
        "type": "Celebrity"
    },
    {
        "name": "Top Athlete #38",
        "netWorth": 121412357.0092282,
        "earningsPerSec": 0.58,
        "source": "Athlete",
        "type": "Celebrity"
    },
    {
        "name": "Top Actor #186",
        "netWorth": 120016971.06909437,
        "earningsPerSec": 0.57,
        "source": "Actor",
        "type": "Celebrity"
    },
    {
        "name": "Top Athlete #94",
        "netWorth": 112560272.27529617,
        "earningsPerSec": 0.54,
        "source": "Athlete",
        "type": "Celebrity"
    },
    {
        "name": "Top Athlete #159",
        "netWorth": 109502861.49082515,
        "earningsPerSec": 0.52,
        "source": "Athlete",
        "type": "Celebrity"
    },
    {
        "name": "Top Influencer #183",
        "netWorth": 99880408.0457537,
        "earningsPerSec": 0.48,
        "source": "Influencer",
        "type": "Celebrity"
    },
    {
        "name": "Top Actor #145",
        "netWorth": 96080678.79237758,
        "earningsPerSec": 0.46,
        "source": "Actor",
        "type": "Celebrity"
    },
    {
        "name": "Top Director #91",
        "netWorth": 93648476.52439976,
        "earningsPerSec": 0.45,
        "source": "Director",
        "type": "Celebrity"
    },
    {
        "name": "Top Actor #42",
        "netWorth": 88284683.33757459,
        "earningsPerSec": 0.42,
        "source": "Actor",
        "type": "Celebrity"
    },
    {
        "name": "Top Singer #70",
        "netWorth": 88214506.85905598,
        "earningsPerSec": 0.42,
        "source": "Singer",
        "type": "Celebrity"
    },
    {
        "name": "Top Athlete #29",
        "netWorth": 87631096.97311701,
        "earningsPerSec": 0.42,
        "source": "Athlete",
        "type": "Celebrity"
    },
    {
        "name": "Top Singer #164",
        "netWorth": 83199387.89204027,
        "earningsPerSec": 0.4,
        "source": "Singer",
        "type": "Celebrity"
    },
    {
        "name": "Top Athlete #47",
        "netWorth": 82890680.47881187,
        "earningsPerSec": 0.39,
        "source": "Athlete",
        "type": "Celebrity"
    },
    {
        "name": "Top Singer #179",
        "netWorth": 80646300.35116167,
        "earningsPerSec": 0.38,
        "source": "Singer",
        "type": "Celebrity"
    },
    {
        "name": "Top Influencer #120",
        "netWorth": 79360980.0675879,
        "earningsPerSec": 0.38,
        "source": "Influencer",
        "type": "Celebrity"
    },
    {
        "name": "Top Director #166",
        "netWorth": 67810965.17575437,
        "earningsPerSec": 0.32,
        "source": "Director",
        "type": "Celebrity"
    },
    {
        "name": "Top Influencer #41",
        "netWorth": 62301004.36548816,
        "earningsPerSec": 0.3,
        "source": "Influencer",
        "type": "Celebrity"
    },
    {
        "name": "Top Actor #74",
        "netWorth": 60395327.47961351,
        "earningsPerSec": 0.29,
        "source": "Actor",
        "type": "Celebrity"
    },
    {
        "name": "Top Singer #147",
        "netWorth": 59930856.92504074,
        "earningsPerSec": 0.29,
        "source": "Singer",
        "type": "Celebrity"
    },
    {
        "name": "Top Athlete #44",
        "netWorth": 58043304.66152877,
        "earningsPerSec": 0.28,
        "source": "Athlete",
        "type": "Celebrity"
    },
    {
        "name": "Top Director #31",
        "netWorth": 54924904.62974138,
        "earningsPerSec": 0.26,
        "source": "Director",
        "type": "Celebrity"
    },
    {
        "name": "Top Influencer #153",
        "netWorth": 54525008.37860415,
        "earningsPerSec": 0.26,
        "source": "Influencer",
        "type": "Celebrity"
    },
    {
        "name": "Top Director #130",
        "netWorth": 29040518.692947403,
        "earningsPerSec": 0.14,
        "source": "Director",
        "type": "Celebrity"
    },
    {
        "name": "Top Director #152",
        "netWorth": 28416657.135344546,
        "earningsPerSec": 0.14,
        "source": "Director",
        "type": "Celebrity"
    },
    {
        "name": "Top Director #107",
        "netWorth": 27399912.234211955,
        "earningsPerSec": 0.13,
        "source": "Director",
        "type": "Celebrity"
    },
    {
        "name": "Top Athlete #118",
        "netWorth": 15166954.032086197,
        "earningsPerSec": 0.07,
        "source": "Athlete",
        "type": "Celebrity"
    },
    {
        "name": "Top Singer #194",
        "netWorth": 11431093.079979626,
        "earningsPerSec": 0.05,
        "source": "Singer",
        "type": "Celebrity"
    }
]